[{"id":1,"name":"Leanne Graham","username":"Bret"},{"id":2,"name":"Ervin Howell","username":"Antonette"},{"id":3,"name":"Clementine Bauch","username":"Samantha"},{"id":4,"name":"Patricia Lebsack","username":"Karianne"},{"id":5,"name":"Chelsey Dietrich","username":"Kamren"},{"id":6,"name":"Mrs. Dennis Schulist","username":"Leopoldo_Corkery"},{"id":7,"name":"Kurtis Weissnat","username":"Elwyn.Skiles"},{"id":8,"name":"Nicholas Runolfsdottir V","username":"Maxime_Nienow"},{"id":9,"name":"Glenna Reichert","username":"Delphine"},{"id":10,"name":"Clementina DuBuque","username":"Moriah.Stanton"},{"id":11,"name":"dsfa","username":"safd"},{"id":12,"name":"asdfsadgd","username":"dsgfsdgf"},{"id":15,"name":"sdfg","username":"sdfg"},{"id":14,"name":"gfhj","username":"gfhj"},{"id":13,"name":"asdfasgfh","username":"dfhgsfhd"},{"id":16,"name":"asdfsf","username":"safdhgdhg"},{"id":16,"name":"asdfs","username":"xxxxxxxxx"}]